{
  "id": "jordayne",
  "name": "Jordayne",
  "emoji": "",
  "words": "Let it be Written",
  "arms": [
    {
      "path": "/images/houses/jordayne.svg",
      "creator": "https://awoiaf.westeros.org/index.php/User:Abjiklam",
      "license": "https://creativecommons.org/licenses/by-sa/3.0/",
      "original_url": "https://awoiaf.westeros.org/index.php/File:House_Jordayne.svg",
      "original_object": {
        "timestamp": "2018-10-23T17:56:21Z",
        "user": "Abjiklam",
        "size": 6727,
        "width": 600,
        "height": 600,
        "url": "https://awoiaf.westeros.org/images/6/68/House_Jordayne.svg",
        "descriptionurl": "https://awoiaf.westeros.org/index.php/File:House_Jordayne.svg",
        "descriptionshorturl": "https://awoiaf.westeros.org/index.php?curid=22628",
        "metadata": [
          {
            "name": "version",
            "value": 2
          },
          {
            "name": "width",
            "value": 600
          },
          {
            "name": "height",
            "value": 600
          },
          {
            "name": "originalWidth",
            "value": "600"
          },
          {
            "name": "originalHeight",
            "value": "600"
          },
          {
            "name": "translations",
            "value": []
          }
        ],
        "exif": {
          "version": 2,
          "width": 600,
          "height": 600,
          "originalWidth": "600",
          "originalHeight": "600",
          "translations": []
        }
      }
    }
  ],
  "region": "dorne",
  "colors": [
    {
      "hex": "#00cc00",
      "rgb": [
        0,
        204,
        0
      ],
      "tput": 41,
      "basic": "green",
      "html": "limegreen",
      "ntc": "Malachite",
      "pantone": "Electric Lime",
      "x11": "limegreen"
    },
    {
      "hex": "#008800",
      "rgb": [
        0,
        136,
        0
      ],
      "tput": 31,
      "basic": "green",
      "html": "green",
      "ntc": "Forest Green",
      "pantone": "Fern",
      "x11": "green"
    },
    {
      "hex": "#ffcc00",
      "rgb": [
        255,
        204,
        0
      ],
      "tput": 239,
      "basic": "gold",
      "html": "gold",
      "ntc": "Supernova",
      "pantone": "Sunglow",
      "x11": "gold"
    },
    {
      "hex": "#ffee33",
      "rgb": [
        255,
        238,
        51
      ],
      "tput": 244,
      "basic": "gold",
      "html": "gold",
      "ntc": "Lemon",
      "pantone": "Laser Lemon",
      "x11": "gold"
    },
    {
      "hex": "#aaaa00",
      "rgb": [
        170,
        170,
        0
      ],
      "tput": 157,
      "basic": "gold",
      "html": "olive",
      "ntc": "Citron",
      "pantone": "Sunglow",
      "x11": "olive"
    },
    {
      "hex": "#000000",
      "rgb": [
        0,
        0,
        0
      ],
      "tput": 16,
      "basic": "black",
      "html": "black",
      "ntc": "Black",
      "pantone": "Black",
      "x11": "black"
    },
    {
      "hex": "#ffffff",
      "rgb": [
        255,
        255,
        255
      ],
      "tput": 252,
      "basic": "white",
      "html": "white",
      "ntc": "White",
      "pantone": "White",
      "x11": "white"
    },
    {
      "hex": "#666666",
      "rgb": [
        102,
        102,
        102
      ],
      "tput": 88,
      "basic": "gray",
      "html": "dimgray",
      "ntc": "Storm Dust",
      "pantone": "Outer Space",
      "x11": "dimgray"
    }
  ]
}